sm_datasets/__init__.py
sm_datasets/datasets.py
sm_datasets/helper.py
sm_datasets/migrations/__init__.py
sm_datasets/migrations/biotables.py
sm_datasets/migrations/semtab.py
sm_datasets/migrations/semtab2020.py
sm_datasets/migrations/semtab2020_r4sampled.py
sm_datasets/migrations/semtab2022.py
sm_datasets/models.py
sm_datasets/verrsion_compare.ipynb
sm_datasets-2.0.2.dist-info/METADATA
sm_datasets-2.0.2.dist-info/WHEEL
sm_datasets-2.0.2.dist-info/RECORD
