Metadata-Version: 2.1
Name: sm-datasets
Version: 2.0.2
Summary: Datasets for benchmarking Semantic Modeling problem
License: MIT
Author: Binh Vu
Author-email: binh@toan2.com
Requires-Python: >=3.9,<4.0
Classifier: License :: OSI Approved :: MIT License
Classifier: Programming Language :: Python :: 3
Classifier: Programming Language :: Python :: 3.9
Classifier: Programming Language :: Python :: 3.10
Classifier: Programming Language :: Python :: 3.11
Classifier: Programming Language :: Python :: 3.12
Requires-Dist: kgdata (>=6.0.0,<7.0.0)
Requires-Dist: loguru (>=0.7.0,<0.8.0)
Requires-Dist: python-slugify (>=6.1.2,<7.0.0)
Requires-Dist: rdflib (>=6.1.1,<7.0.0)
Requires-Dist: sem-desc (>=6.0.0,<7.0.0)
